entity_selector_jupyter_widget/__init__.py
entity_selector_jupyter_widget/_version.py
entity_selector_jupyter_widget/entity_selector.py
entity_selector_jupyter_widget/widget.py
entity_selector_jupyter_widget/static/extension.js
entity_selector_jupyter_widget/static/index.js
entity_selector_jupyter_widget/static/index.js.map
entity_selector_jupyter_widget-0.1.6.data/data/etc/jupyter/nbconfig/notebook.d/frontend_entity_selector_jupyter_widget.json
entity_selector_jupyter_widget-0.1.6.data/data/share/jupyter/nbextensions/frontend_entity_selector_jupyter_widget/extension.js
entity_selector_jupyter_widget-0.1.6.data/data/share/jupyter/nbextensions/frontend_entity_selector_jupyter_widget/index.js
entity_selector_jupyter_widget-0.1.6.data/data/share/jupyter/nbextensions/frontend_entity_selector_jupyter_widget/index.js.map
entity_selector_jupyter_widget-0.1.6.dist-info/LICENSE
entity_selector_jupyter_widget-0.1.6.dist-info/METADATA
entity_selector_jupyter_widget-0.1.6.dist-info/WHEEL
entity_selector_jupyter_widget-0.1.6.dist-info/top_level.txt
entity_selector_jupyter_widget-0.1.6.dist-info/RECORD
