Metadata-Version: 2.1
Name: entity-selector-jupyter-widget
Version: 0.1.6
Summary: A Jupyter Widget library for selecting entities in text
Home-page: https://gitlab.com/randomunrandom/entity_selector_jupyter_widget
Author: Danil Kireev
Author-email: randomunrandom@yandex.ru
License: UNKNOWN
Keywords: ipython,jupyter,widgets
Platform: UNKNOWN
Classifier: Development Status :: 4 - Beta
Classifier: Framework :: IPython
Classifier: License :: OSI Approved :: MIT License
Classifier: Intended Audience :: Developers
Classifier: Intended Audience :: Science/Research
Classifier: Topic :: Multimedia :: Graphics
Classifier: Programming Language :: Python :: 2
Classifier: Programming Language :: Python :: 2.7
Classifier: Programming Language :: Python :: 3
Classifier: Programming Language :: Python :: 3.3
Classifier: Programming Language :: Python :: 3.4
Classifier: Programming Language :: Python :: 3.5
Requires-Dist: ipywidgets
